chartx
