Metadata-Version: 2.1
Name: chartx
Version: 0.1.3
Summary: A curated amalgam of financial helpers in Python
Author: Taha Shieenavaz
Author-email: tahashieenavaz@gmail.com
License-File: LICENSE
